pulseaudio_simple_loopback/__init__.py
pulseaudio_simple_loopback/loopback_setup.py
pulseaudio_simple_loopback/loopback_stop.py
pulseaudio_simple_loopback-1.0.0.dist-info/licenses/LICENSE
pulseaudio_simple_loopback-1.0.0.dist-info/METADATA
pulseaudio_simple_loopback-1.0.0.dist-info/WHEEL
pulseaudio_simple_loopback-1.0.0.dist-info/entry_points.txt
pulseaudio_simple_loopback-1.0.0.dist-info/top_level.txt
pulseaudio_simple_loopback-1.0.0.dist-info/RECORD
