Metadata-Version: 2.4
Name: pulseaudio-simple-loopback
Version: 1.0.0
Summary: A simple CLI script to setup PulseAudio loopbacks
Author: Rafał Kalisz
License: MIT
License-File: LICENSE
Requires-Dist: rich
Dynamic: license-file
